strawberry/__init__.py
strawberry/__main__.py
strawberry/aiohttp/__init__.py
strawberry/aiohttp/handlers/__init__.py
strawberry/aiohttp/handlers/graphql_transport_ws_handler.py
strawberry/aiohttp/handlers/graphql_ws_handler.py
strawberry/aiohttp/handlers/http_handler.py
strawberry/aiohttp/test/__init__.py
strawberry/aiohttp/test/client.py
strawberry/aiohttp/views.py
strawberry/annotation.py
strawberry/arguments.py
strawberry/asgi/__init__.py
strawberry/asgi/handlers/__init__.py
strawberry/asgi/handlers/graphql_transport_ws_handler.py
strawberry/asgi/handlers/graphql_ws_handler.py
strawberry/asgi/handlers/http_handler.py
strawberry/asgi/test/__init__.py
strawberry/asgi/test/client.py
strawberry/auto.py
strawberry/chalice/__init__.py
strawberry/chalice/views.py
strawberry/channels/__init__.py
strawberry/channels/context.py
strawberry/channels/handlers/base.py
strawberry/channels/handlers/graphql_transport_ws_handler.py
strawberry/channels/handlers/graphql_ws_handler.py
strawberry/channels/handlers/http_handler.py
strawberry/channels/handlers/ws_handler.py
strawberry/channels/router.py
strawberry/channels/testing.py
strawberry/cli/__init__.py
strawberry/cli/commands/__init__.py
strawberry/cli/commands/codegen.py
strawberry/cli/commands/export_schema.py
strawberry/cli/commands/server.py
strawberry/cli/constants.py
strawberry/cli/debug_server.py
strawberry/cli/utils/__init__.py
strawberry/cli/utils/load_schema.py
strawberry/codegen/__init__.py
strawberry/codegen/exceptions.py
strawberry/codegen/plugins/__init__.py
strawberry/codegen/plugins/print_operation.py
strawberry/codegen/plugins/python.py
strawberry/codegen/plugins/typescript.py
strawberry/codegen/query_codegen.py
strawberry/codegen/types.py
strawberry/custom_scalar.py
strawberry/dataloader.py
strawberry/directive.py
strawberry/django/__init__.py
strawberry/django/apps.py
strawberry/django/context.py
strawberry/django/test/__init__.py
strawberry/django/test/client.py
strawberry/django/views.py
strawberry/enum.py
564bff00ff_strawberry_graphql-0.168.2.dist-info/LICENSE
564bff00ff_strawberry_graphql-0.168.2.dist-info/METADATA
564bff00ff_strawberry_graphql-0.168.2.dist-info/WHEEL
564bff00ff_strawberry_graphql-0.168.2.dist-info/entry_points.txt
564bff00ff_strawberry_graphql-0.168.2.dist-info/RECORD
