Metadata-Version: 2.1
Name: 564bff00ff-strawberry-graphql
Version: 0.168.2
Summary: A library for creating GraphQL APIs
Home-page: https://strawberry.rocks/
License: MIT
Keywords: graphql,api,rest,starlette,async
Author: Patrick Arminio
Author-email: patrick.arminio@gmail.com
Requires-Python: >=3.7,<4.0
Classifier: Development Status :: 5 - Production/Stable
Classifier: Intended Audience :: Developers
Classifier: License :: OSI Approved :: MIT License
Classifier: Programming Language :: Python :: 3
Classifier: Programming Language :: Python :: 3.7
Classifier: Programming Language :: Python :: 3.8
Classifier: Programming Language :: Python :: 3.9
Classifier: Programming Language :: Python :: 3.10
Classifier: Programming Language :: Python :: 3.11
Classifier: Topic :: Software Development :: Libraries
Classifier: Topic :: Software Development :: Libraries :: Python Modules
Provides-Extra: aiohttp
Provides-Extra: asgi
Provides-Extra: chalice
Provides-Extra: channels
Provides-Extra: cli
Provides-Extra: debug
Provides-Extra: debug-server
Provides-Extra: django
Provides-Extra: fastapi
Provides-Extra: flask
Provides-Extra: opentelemetry
Provides-Extra: pydantic
Provides-Extra: sanic
Provides-Extra: starlite
Requires-Dist: Django (>=3.2) ; extra == "django"
Requires-Dist: aiohttp (>=3.7.4.post0,<4.0.0) ; extra == "aiohttp"
Requires-Dist: asgiref (>=3.2,<4.0) ; extra == "django" or extra == "channels"
Requires-Dist: astunparse (>=1.6.3,<2.0.0) ; python_version < "3.9"
Requires-Dist: backports.cached-property (>=1.0.2,<2.0.0) ; python_version < "3.8"
Requires-Dist: chalice (>=1.22,<2.0) ; extra == "chalice"
Requires-Dist: channels (>=3.0.5) ; extra == "channels"
Requires-Dist: click (>=7.0,<9.0) ; extra == "debug-server" or extra == "cli"
Requires-Dist: fastapi (>=0.65.2) ; extra == "fastapi"
Requires-Dist: flask (>=1.1) ; extra == "flask"
Requires-Dist: graphql-core (>=3.2.0,<3.3.0)
Requires-Dist: libcst (>=0.4.7) ; extra == "debug" or extra == "debug-server" or extra == "cli"
Requires-Dist: opentelemetry-api (<2) ; extra == "opentelemetry"
Requires-Dist: opentelemetry-sdk (<2) ; extra == "opentelemetry"
Requires-Dist: pydantic (<2) ; extra == "pydantic"
Requires-Dist: pygments (>=2.3,<3.0) ; extra == "debug-server" or extra == "cli"
Requires-Dist: python-dateutil (>=2.7.0,<3.0.0)
Requires-Dist: python-multipart (>=0.0.5,<0.0.7) ; extra == "asgi" or extra == "debug-server" or extra == "fastapi"
Requires-Dist: rich (>=12.0.0) ; extra == "debug" or extra == "debug-server" or extra == "cli"
Requires-Dist: sanic (>=20.12.2) ; extra == "sanic"
Requires-Dist: starlette (>=0.18.0) ; extra == "asgi" or extra == "debug-server"
Requires-Dist: starlite (>=1.48.0) ; (python_version >= "3.8") and (extra == "starlite")
Requires-Dist: typing_extensions (>=3.7.4,<5.0.0)
Requires-Dist: uvicorn (>=0.11.6,<0.22.0) ; extra == "debug-server"
Project-URL: Changelog, https://strawberry.rocks/changelog
Project-URL: Documentation, https://strawberry.rocks/
Project-URL: Discord, https://discord.com/invite/3uQ2PaY
Project-URL: Mastodon, https://farbun.social/@strawberry
Project-URL: Repository, https://github.com/strawberry-graphql/strawberry
Project-URL: Sponsor on GitHub, https://github.com/sponsors/strawberry-graphql
Project-URL: Sponsor on Open Collective, https://opencollective.com/strawberry-graphql
Project-URL: Twitter, https://twitter.com/strawberry_gql
